{
    "menu": [
      {
        "name": "CLEARENCE",
        "subcategories": [],
        "links":"/"
      },
      {
        "name": "ISHO BUSSINESS",
        "subcategories": [],
        "links":"/login"
      },
      {
        "name": "COLLECTIONS",
        "subcategories": [
          "ALFELD",
          "AVESTA",
          "BOPPARD",
          "BRERA",
          "BUSHWICK",
          "CHESTERFIELD",
          "DALIAN",
          "DESSAU",
          "ELGIN",
          "ELLIOT",
          "FLEXI",
          "GIOCO",
          "IKAT",
          "JORASANKO",
          "KASHAN",
          "KNOLE",
          "KOWLOON",
          "MALMO",
          "MELROSE",
          "MOD POD",
          "MONTPELLIER",
          "MONZA",
          "MORANDI",
          "MUKŌ",
          "MYSURU",
          "NADOR",
          "NAKSHIKATHA",
          "NAVIGLI",
          "NINO",
          "NOBLITT",
          "OREBRO",
          "OSTRAVA",
          "PALERMO",
          "PEBBLE",
          "POMPEII",
          "PRESTON",
          "RATARGUL",
          "ROSEWALL",
          "SHEFFIELD",
          "SMITHFIELD",
          "SOHO",
          "SONARGAON",
          "ST. PAULI",
          "SMART",
          "TERTRE",
          "TORA",
          "VESTERBRO",
          "WILLIAMSBURG"
        ]
      },
      {
        "name": "DESIGN STUDIO",
        "subcategories": [],
        "links":"/"
      },
      {
        "name": "INNVATION",
        "subcategories": []
      },
      {
        "name": "IDEAS",
        "subcategories": []
      },
      {
        "name": "GIFT",
        "subcategories": []
      }
    ]
  }
  